exporteer_todoist/__init__.py
exporteer_todoist/__main__.py
exporteer_todoist/cli.py
exporteer_todoist-0.0.1.dist-info/LICENSE
exporteer_todoist-0.0.1.dist-info/METADATA
exporteer_todoist-0.0.1.dist-info/WHEEL
exporteer_todoist-0.0.1.dist-info/entry_points.txt
exporteer_todoist-0.0.1.dist-info/top_level.txt
exporteer_todoist-0.0.1.dist-info/RECORD
