Metadata-Version: 2.1
Name: exporteer-todoist
Version: 0.0.1
Summary: Downloads data from Todoist and saves it to the filesystem.
Home-page: https://github.com/brokensandals/exporteer_todoist
Author: Jacob Williams
Author-email: jacobaw@gmail.com
License: UNKNOWN
Platform: UNKNOWN
Classifier: Programming Language :: Python :: 3
Classifier: License :: OSI Approved :: MIT License
Classifier: Operating System :: OS Independent
Requires-Python: >=3.7
Requires-Dist: requests (>=2)
